{
    "rakosi": {
        "Name": "Rákosi-korszak",
        "Group": "Újkor",
        "Time": { "Start": "1948.1.1.", "End": "1956.10.23." },
        "ImageSources": {
            "1.jpg": { "Label": "Történelem tankönyv 12.", "Url": "https://www.tankonyvkatalogus.hu/site/kiadvany/OH-TOR12TB" }
        }
    },
    "56": {
        "Name": "1956-os forradalom és szabadságharc",
        "Group": "Újkor",
        "Time": "1956.10.23.",
        "ImageSources": {
            "1.jpg": { "Label": "Történelem tankönyv 12.", "Url": "https://www.tankonyvkatalogus.hu/site/kiadvany/OH-TOR12TB" }
        }
    },
    "kadar": {
        "Name": "Kádár-korszak",
        "Group": "Újkor",
        "Time": { "Start": "1956.10.23.", "End": "1989.1.1." },
        "ImageSources": {
            "1.jpg": { "Label": "Történelem tankönyv 12.", "Url": "https://www.tankonyvkatalogus.hu/site/kiadvany/OH-TOR12TB" }
        }
    },
    "horthy": {
        "Name": "Horthy-korszak",
        "Group": "Újkor",
        "Time": { "Start": "1920.1.1.", "End": "1946.12.31." },
        "ImageSources": { }
    },
    "mo-vh-1": {
        "Name": "Magyarország a 2 vh. időszakában",
        "Group": "Újkor",
        "ImageSources": { }
    },
    "atheni-demokracia": {
        "Name": "Az athéni demokrácia",
        "Group": "Ókor",
        "ImageSources": { }
    },
    "gorog-romai-epiteszet": {
        "Name": "A görög és római építészet",
        "Group": "Ókor",
        "ImageSources": { }
    },
    "kozepkor-mezogazdasag": {
        "Name": "A mezőgazdasági technika változásai",
        "Group": "Középkor",
        "ImageSources": { }
    },
    "kozepkor-varosok": {
        "Name": "A középkori városok kialakulása és a városok jogai",
        "Group": "Középkor",
        "ImageSources": { }
    },
    "mariaterezia": {
        "Name": "Mária Terézia",
        "Group": "Középkor",
        "ImageSources": { }
    },
    "eu": {
        "Name": "Európai unió",
        "Group": "Újkor",
        "ImageSources": { }
    },
    "aranybulla": {
        "Name": "Aranybulla",
        "Group": "Középkor",
        "ImageSources": { }
    },
    "naci": {
        "Name": "Nácik",
        "Group": "Újkor",
        "ImageSources": { }
    },
    "ww2": {
        "Name": "II. Világháború",
        "Group": "Újkor",
        "ImageSources": { }
    },
    "ww2-elozmenyek": {
        "Name": "II. Világháború előzményei",
        "Group": "Újkor",
        "ImageSources": { }
    }
}
